{
  "_class": "shapeGroup",
  "clippingMaskMode": 0,
  "do_objectID": "8D0D8DEB-23B2-416E-88E6-8AC82F20FA89",
  "exportOptions": {
    "_class": "exportOptions",
    "do_objectID": "D2857288-14FE-4B8C-B7AB-BD9B3F60BC5D",
    "exportFormats": [
    ],
    "includedLayerIds": [
    ],
    "layerOptions": 0,
    "shouldTrim": false
  },
  "frame": {
    "_class": "rect",
    "constrainProportions": false,
    "do_objectID": "1426FDC1-7CD2-4245-8DB0-6A588BD1F191",
    "height": 40,
    "width": 375,
    "x": 0,
    "y": 0
  },
  "hasClickThrough": true,
  "hasClippingMask": false,
  "isFlippedHorizontal": false,
  "isFlippedVertical": false,
  "isLocked": false,
  "isVisible": true,
  "layerListExpandedType": 2,
  "layers": [
    {
      "class": "rectangle",
      "id": "B7621C8F-F2F2-4509-B0C3-B9538501C1D0"
    }
  ],
  "name": "SubHeader",
  "nameIsFixed": true,
  "resizingConstraint": 63,
  "resizingType": 0,
  "rotation": 0,
  "shouldBreakMaskChain": false,
  "style": {
    "_class": "style",
    "borders": [
      {
        "_class": "border",
        "color": {
          "_class": "color",
          "alpha": 1,
          "blue": 0.592,
          "green": 0.592,
          "red": 0.592
        },
        "fillType": 0,
        "isEnabled": false,
        "position": 1,
        "thickness": 1
      }
    ],
    "do_objectID": "AAFD4B33-BDC2-4DEB-B337-A5959D2E7322",
    "endDecorationType": 0,
    "fills": [
      {
        "_class": "fill",
        "color": {
          "_class": "color",
          "alpha": 1,
          "blue": 0.2588235294117647,
          "green": 0.2588235294117647,
          "red": 0.2588235294117647
        },
        "fillType": 0,
        "isEnabled": true,
        "noiseIndex": 0,
        "noiseIntensity": 0,
        "patternFillType": 0,
        "patternTileScale": 1
      }
    ],
    "miterLimit": 10,
    "shadows": [
      {
        "_class": "shadow",
        "blurRadius": 4,
        "color": {
          "_class": "color",
          "alpha": 0.5,
          "blue": 0,
          "green": 0,
          "red": 0
        },
        "contextSettings": {
          "_class": "graphicsContextSettings",
          "blendMode": 0,
          "opacity": 1
        },
        "isEnabled": false,
        "offsetX": 0,
        "offsetY": 2,
        "spread": 0
      }
    ],
    "startDecorationType": 0
  },
  "windingRule": 1
}