{
  "_class": "shapeGroup",
  "clippingMaskMode": 0,
  "do_objectID": "76B7B8DB-A069-4FF1-A509-5E74572F289A",
  "exportOptions": {
    "_class": "exportOptions",
    "do_objectID": "DFC3E654-AEF3-4139-888B-98B1D2298D8B",
    "exportFormats": [
    ],
    "includedLayerIds": [
    ],
    "layerOptions": 0,
    "shouldTrim": false
  },
  "frame": {
    "_class": "rect",
    "constrainProportions": false,
    "do_objectID": "A9C5A35C-73CC-4DB4-92FC-50D354B11FC6",
    "height": 50,
    "width": 160,
    "x": 175,
    "y": 65
  },
  "hasClickThrough": true,
  "hasClippingMask": false,
  "isFlippedHorizontal": false,
  "isFlippedVertical": false,
  "isLocked": false,
  "isVisible": true,
  "layerListExpandedType": 0,
  "layers": [
    {
      "class": "rectangle",
      "id": "F489671A-7301-431A-A16A-68F4CA5EB48E"
    }
  ],
  "name": "Btn 1 Copy 4",
  "nameIsFixed": true,
  "resizingConstraint": 63,
  "resizingType": 0,
  "rotation": 0,
  "shouldBreakMaskChain": false,
  "style": {
    "_class": "style",
    "borders": [
      {
        "_class": "border",
        "color": {
          "_class": "color",
          "alpha": 1,
          "blue": 0.4838,
          "green": 0.8200000000000001,
          "red": 0.6631066666666667
        },
        "fillType": 0,
        "isEnabled": true,
        "position": 1,
        "thickness": 1
      }
    ],
    "do_objectID": "780A8D40-C6BD-47B6-9E48-BD3D081D7A5C",
    "endDecorationType": 0,
    "fills": [
      {
        "_class": "fill",
        "color": {
          "_class": "color",
          "alpha": 1,
          "blue": 0.4,
          "green": 0.2801333333333333,
          "red": 0.276
        },
        "fillType": 1,
        "gradient": {
          "_class": "gradient",
          "elipseLength": 0,
          "from": "{0.5, 0.021631141618497111}",
          "gradientType": 0,
          "stops": [
            {
              "_class": "gradientStop",
              "color": {
                "_class": "color",
                "alpha": 1,
                "blue": 0.4,
                "green": 0.2784313725490196,
                "red": 0.2745098039215687
              },
              "position": 0
            },
            {
              "_class": "gradientStop",
              "color": {
                "_class": "color",
                "alpha": 1,
                "blue": 0.25,
                "green": 0.1750833333333333,
                "red": 0.1725
              },
              "position": 1
            }
          ],
          "to": "{0.5, 0.95905557673424102}"
        },
        "isEnabled": true,
        "noiseIndex": 0,
        "noiseIntensity": 0,
        "patternFillType": 0,
        "patternTileScale": 1
      }
    ],
    "miterLimit": 10,
    "startDecorationType": 0
  },
  "windingRule": 1
}