{
  "_class": "shapePath",
  "booleanOperation": -1,
  "do_objectID": "D21295B8-9BA4-4BAE-90E6-3A5F787E68EA",
  "edited": true,
  "exportOptions": {
    "_class": "exportOptions",
    "do_objectID": "8B03AF82-746F-4535-B77C-F2F6F3D71787",
    "exportFormats": [
    ],
    "includedLayerIds": [
    ],
    "layerOptions": 0,
    "shouldTrim": false
  },
  "frame": {
    "_class": "rect",
    "constrainProportions": false,
    "do_objectID": "9326F372-8A09-43E5-B3A8-B596F8A0CC83",
    "height": 4,
    "width": 9,
    "x": 7.999999999999991,
    "y": 5.000000000000021
  },
  "isClosed": true,
  "isFlippedHorizontal": false,
  "isFlippedVertical": false,
  "isLocked": false,
  "isVisible": true,
  "layerListExpandedType": 0,
  "name": "Path",
  "nameIsFixed": false,
  "pointRadiusBehaviour": 1,
  "points": [
    {
      "_class": "curvePoint",
      "cornerRadius": 0,
      "curveFrom": "{0.95734141297552056, 0.39501378100726675}",
      "curveMode": 4,
      "curveTo": "{1, 1}",
      "hasCurveFrom": true,
      "hasCurveTo": false,
      "point": "{1, 1}"
    },
    {
      "_class": "curvePoint",
      "cornerRadius": 0,
      "curveFrom": "{0.26056846053960492, 0}",
      "curveMode": 3,
      "curveTo": "{0.74409657096138282, 0}",
      "hasCurveFrom": true,
      "hasCurveTo": true,
      "point": "{0.51180685807723991, 0}"
    },
    {
      "_class": "curvePoint",
      "cornerRadius": 0,
      "curveFrom": "{0, 1}",
      "curveMode": 4,
      "curveTo": "{0.052084836242967655, 0.34577800050112789}",
      "hasCurveFrom": false,
      "hasCurveTo": true,
      "point": "{0, 1}"
    }
  ],
  "resizingConstraint": 63,
  "resizingType": 0,
  "rotation": 0,
  "shouldBreakMaskChain": false
}