{
  "_class": "shapePath",
  "booleanOperation": -1,
  "do_objectID": "8A50BF2F-AF4E-4CDC-8C8A-969DDF0DB847",
  "edited": true,
  "exportOptions": {
    "_class": "exportOptions",
    "do_objectID": "B7976422-94D0-46AE-9A27-D017CA015C98",
    "exportFormats": [
    ],
    "includedLayerIds": [
    ],
    "layerOptions": 0,
    "shouldTrim": false
  },
  "frame": {
    "_class": "rect",
    "constrainProportions": false,
    "do_objectID": "1120E40F-19BF-4C0F-B427-C484F9F46189",
    "height": 3,
    "width": 330,
    "x": 0,
    "y": 0
  },
  "isClosed": false,
  "isFlippedHorizontal": false,
  "isFlippedVertical": false,
  "isLocked": false,
  "isVisible": true,
  "layerListExpandedType": 0,
  "name": "Path",
  "nameIsFixed": false,
  "pointRadiusBehaviour": 1,
  "points": [
    {
      "_class": "curvePoint",
      "cornerRadius": 0,
      "curveFrom": "{0.0030303030303030346, 0.66666666666666674}",
      "curveMode": 1,
      "curveTo": "{0.0030303030303030346, 0.66666666666666674}",
      "hasCurveFrom": false,
      "hasCurveTo": false,
      "point": "{0.0015151515151515162, 0.49999999999999994}"
    },
    {
      "_class": "curvePoint",
      "cornerRadius": 0,
      "curveFrom": "{0.0060606060606060649, 1}",
      "curveMode": 1,
      "curveTo": "{0.0060606060606060649, 1}",
      "hasCurveFrom": false,
      "hasCurveTo": false,
      "point": "{0.99848945379796605, 0.49999999999999994}"
    }
  ],
  "resizingConstraint": 63,
  "resizingType": 0,
  "rotation": 0,
  "shouldBreakMaskChain": false
}